MANIFEST.in
setup.py
snort/__init__.py
snort/__version__.py
snort/failure.png
snort/generic_plugin.py
snort/nose_plugin.py
snort/python.png
snort/skip.png
snort/success.png
snort.egg-info/PKG-INFO
snort.egg-info/SOURCES.txt
snort.egg-info/dependency_links.txt
snort.egg-info/entry_points.txt
snort.egg-info/namespace_packages.txt
snort.egg-info/not-zip-safe
snort.egg-info/top_level.txt