Metadata-Version: 1.0
Name: snort
Version: 0.0.7
Summary: (Yet another) nosetests growl plugin, using growlnotify
Home-page: UNKNOWN
Author: Rotem Yaari
Author-email: vmalloc@gmail.com
License: BSD
Platform: UNKNOWN
Classifier: Programming Language :: Python :: 2.6
